odoo/addons/mail_drop_target/README.rst
odoo/addons/mail_drop_target/__init__.py
odoo/addons/mail_drop_target/__manifest__.py
odoo/addons/mail_drop_target/i18n/mail_drop_target.pot
odoo/addons/mail_drop_target/models/__init__.py
odoo/addons/mail_drop_target/models/mail_message.py
odoo/addons/mail_drop_target/models/mail_thread.py
odoo/addons/mail_drop_target/models/res_config_settings.py
odoo/addons/mail_drop_target/readme/CONFIGURATION.rst
odoo/addons/mail_drop_target/readme/CONTRIBUTORS.rst
odoo/addons/mail_drop_target/readme/DESCRIPTION.rst
odoo/addons/mail_drop_target/readme/ROADMAP.rst
odoo/addons/mail_drop_target/readme/USAGE.rst
odoo/addons/mail_drop_target/static/description/icon.png
odoo/addons/mail_drop_target/static/description/index.html
odoo/addons/mail_drop_target/static/src/css/mail_drop_target.css
odoo/addons/mail_drop_target/static/src/js/mail_drop_target.js
odoo/addons/mail_drop_target/tests/__init__.py
odoo/addons/mail_drop_target/tests/sample.eml
odoo/addons/mail_drop_target/tests/sample.msg
odoo/addons/mail_drop_target/tests/test_mail_drop_target.py
odoo/addons/mail_drop_target/views/res_config_settings_views.xml
odoo/addons/mail_drop_target/views/templates.xml
odoo12_addon_mail_drop_target-12.0.1.1.2.dist-info/METADATA
odoo12_addon_mail_drop_target-12.0.1.1.2.dist-info/WHEEL
odoo12_addon_mail_drop_target-12.0.1.1.2.dist-info/top_level.txt
odoo12_addon_mail_drop_target-12.0.1.1.2.dist-info/RECORD
