Metadata-Version: 2.1
Name: odoo12-addon-mail-drop-target
Version: 12.0.1.1.2
Summary: Attach emails to Odoo by dragging them from your desktop
Home-page: UNKNOWN
Author: Therp BV,Odoo Community Association (OCA)
Author-email: support@odoo-community.org
License: AGPL-3
Platform: UNKNOWN
Classifier: Programming Language :: Python
Classifier: Framework :: Odoo
Classifier: Framework :: Odoo :: 12.0
Classifier: License :: OSI Approved :: GNU Affero General Public License v3
Requires-Python: >=3.5
Requires-Dist: extract-msg (<0.30)
Requires-Dist: extract-msg
Requires-Dist: odoo12-addon-web-drop-target
Requires-Dist: odoo (<12.1dev,>=12.0a)
